unix_ar.py
unix_ar-0.2.1.dist-info/LICENSE.txt
unix_ar-0.2.1.dist-info/METADATA
unix_ar-0.2.1.dist-info/WHEEL
unix_ar-0.2.1.dist-info/top_level.txt
unix_ar-0.2.1.dist-info/RECORD
