Metadata-Version: 2.1
Name: unix_ar
Version: 0.2.1
Summary: AR file handling
Home-page: https://github.com/getninjas/unix_ar
Author: Remi Rampin
Author-email: remirampin@gmail.com
Maintainer: Alan Justino
Maintainer-email: alan.justino@yahoo.com.br
License: BSD
Keywords: ar,archive,unix,deb
Platform: UNKNOWN
Classifier: Development Status :: 4 - Beta
Classifier: Intended Audience :: Developers
Classifier: License :: OSI Approved :: BSD License
Classifier: Programming Language :: Python :: 3
Classifier: Operating System :: OS Independent
Classifier: Topic :: System :: Archiving
Classifier: Topic :: Utilities
Requires-Python: ~=3.6
